typedspark/__init__.py
typedspark/py.typed
typedspark/_core/__init__.py
typedspark/_core/column.py
typedspark/_core/column_meta.py
typedspark/_core/dataset.py
typedspark/_core/datatypes.py
typedspark/_core/literaltype.py
typedspark/_core/validate_schema.py
typedspark/_schema/__init__.py
typedspark/_schema/dlt_kwargs.py
typedspark/_schema/get_schema_definition.py
typedspark/_schema/get_schema_imports.py
typedspark/_schema/schema.py
typedspark/_schema/structfield.py
typedspark/_transforms/__init__.py
typedspark/_transforms/rename_duplicate_columns.py
typedspark/_transforms/structtype_column.py
typedspark/_transforms/transform_to_schema.py
typedspark/_transforms/utils.py
typedspark/_utils/__init__.py
typedspark/_utils/camelcase.py
typedspark/_utils/create_dataset.py
typedspark/_utils/create_dataset_from_structtype.py
typedspark/_utils/databases.py
typedspark/_utils/load_table.py
typedspark/_utils/pyspark_compat.py
typedspark/_utils/register_schema_to_dataset.py
typedspark-1.6.2.dist-info/licenses/LICENSE.txt
typedspark-1.6.2.dist-info/METADATA
typedspark-1.6.2.dist-info/WHEEL
typedspark-1.6.2.dist-info/top_level.txt
typedspark-1.6.2.dist-info/RECORD
