Metadata-Version: 2.4
Name: typedspark
Version: 1.6.2
Summary: Column-wise type annotations for pyspark DataFrames
Home-page: https://github.com/kaiko-ai/typedspark
Author: Nanne Aben
Author-email: nanne@kaiko.ai
License: Apache-2.0
Keywords: pyspark spark typing type checking annotations
Classifier: Programming Language :: Python
Classifier: Typing :: Typed
Requires-Python: >=3.9.0
License-File: LICENSE.txt
Requires-Dist: typing-extensions<=4.15.0
Provides-Extra: pyspark
Requires-Dist: pyspark; extra == "pyspark"
Dynamic: author
Dynamic: author-email
Dynamic: classifier
Dynamic: description
Dynamic: description-content-type
Dynamic: home-page
Dynamic: keywords
Dynamic: license
Dynamic: license-file
Dynamic: provides-extra
Dynamic: requires-dist
Dynamic: requires-python
Dynamic: summary
